{
    "id": "A336_adStag1.1.13",
    "transcription": "A336",
    "transcription_siglum": "A336",
    "siglum": "A336",
    "context": "adStag1.1.13",
    "n": "adStag1.1.13",
    "plain_text": "σὲ δὲ τοσοῦτον ἕλκοντα χρόνον ἐν νηστείαις καὶ παννυχίσι καὶ τῇ λοιπῇ σκληραγωγίᾳ μηδεμίαν εὑρέσθαι τῶν κατεχόντων δεινῶν",
    "witnesses": [
        {
            "id": "A336",
            "tokens": [
                {
                    "index": "2",
                    "siglum": "A336",
                    "reading": "A336",
                    "original": "σὲ",
                    "rule_match": [
                        "σὲ"
                    ],
                    "t": "σὲ"
                },
                {
                    "index": "4",
                    "siglum": "A336",
                    "reading": "A336",
                    "original": "δὲ",
                    "rule_match": [
                        "δὲ"
                    ],
                    "t": "δὲ"
                },
                {
                    "index": "6",
                    "siglum": "A336",
                    "reading": "A336",
                    "original": "τοσοῦτον",
                    "rule_match": [
                        "τοσοῦτον"
                    ],
                    "t": "τοσοῦτον"
                },
                {
                    "index": "8",
                    "siglum": "A336",
                    "reading": "A336",
                    "original": "ἕλκοντα",
                    "rule_match": [
                        "ἕλκοντα"
                    ],
                    "t": "ἕλκοντα"
                },
                {
                    "index": "10",
                    "siglum": "A336",
                    "reading": "A336",
                    "original": "χρόνον",
                    "rule_match": [
                        "χρόνον"
                    ],
                    "t": "χρόνον"
                },
                {
                    "index": "12",
                    "siglum": "A336",
                    "reading": "A336",
                    "original": "ἐν",
                    "rule_match": [
                        "ἐν"
                    ],
                    "t": "ἐν"
                },
                {
                    "index": "14",
                    "siglum": "A336",
                    "reading": "A336",
                    "original": "νηστείαις",
                    "rule_match": [
                        "νηστείαις"
                    ],
                    "t": "νηστείαις"
                },
                {
                    "index": "16",
                    "siglum": "A336",
                    "reading": "A336",
                    "original": "καὶ",
                    "rule_match": [
                        "καὶ"
                    ],
                    "t": "καὶ"
                },
                {
                    "index": "18",
                    "siglum": "A336",
                    "reading": "A336",
                    "original": "παννυχίσι",
                    "rule_match": [
                        "παννυχίσι"
                    ],
                    "t": "παννυχίσι"
                },
                {
                    "index": "20",
                    "siglum": "A336",
                    "reading": "A336",
                    "original": "καὶ",
                    "rule_match": [
                        "καὶ"
                    ],
                    "t": "καὶ"
                },
                {
                    "index": "22",
                    "siglum": "A336",
                    "reading": "A336",
                    "original": "τῇ",
                    "rule_match": [
                        "τῇ"
                    ],
                    "t": "τῇ"
                },
                {
                    "index": "24",
                    "siglum": "A336",
                    "reading": "A336",
                    "original": "λοιπῇ",
                    "rule_match": [
                        "λοιπῇ"
                    ],
                    "t": "λοιπῇ"
                },
                {
                    "index": "26",
                    "siglum": "A336",
                    "reading": "A336",
                    "original": "σκληραγωγίᾳ",
                    "rule_match": [
                        "σκληραγωγίᾳ"
                    ],
                    "t": "σκληραγωγίᾳ"
                },
                {
                    "index": "28",
                    "siglum": "A336",
                    "reading": "A336",
                    "original": "μηδεμίαν",
                    "rule_match": [
                        "μηδεμίαν"
                    ],
                    "t": "μηδεμίαν"
                },
                {
                    "index": "30",
                    "siglum": "A336",
                    "reading": "A336",
                    "original": "εὑρέσθαι",
                    "rule_match": [
                        "εὑρέσθαι"
                    ],
                    "t": "εὑρέσθαι"
                },
                {
                    "index": "32",
                    "siglum": "A336",
                    "reading": "A336",
                    "original": "τῶν",
                    "rule_match": [
                        "τῶν"
                    ],
                    "t": "τῶν"
                },
                {
                    "index": "34",
                    "siglum": "A336",
                    "reading": "A336",
                    "original": "κατεχόντων",
                    "rule_match": [
                        "κατεχόντων"
                    ],
                    "t": "κατεχόντων"
                },
                {
                    "index": "36",
                    "siglum": "A336",
                    "reading": "A336",
                    "original": "δεινῶν",
                    "rule_match": [
                        "δεινῶν"
                    ],
                    "t": "δεινῶν"
                }
            ]
        }
    ]
}