{
    "id": "Bas_adStag1.1.15",
    "transcription": "Bas",
    "transcription_siglum": "Bas",
    "siglum": "Bas",
    "context": "adStag1.1.15",
    "n": "adStag1.1.15",
    "plain_text": "μετὰ δὲ τούτων καὶ ἑτέρως σφόδρα ἔφης ἀλγεῖν ὅτι οὕτω σου τῆς ψυχῆς ἡ τῆς ἀθυμίας περιεγένετο δύναμις ὡς μικροῦ πολλάκις ἐπὶ βρόχον ἐλθεῖν καὶ ἐπὶ ποταμὸν καὶ ἐπὶ κρημνόν",
    "witnesses": [
        {
            "id": "Bas",
            "tokens": [
                {
                    "index": "2",
                    "siglum": "Bas",
                    "reading": "Bas",
                    "original": "μετὰ",
                    "rule_match": [
                        "μετὰ"
                    ],
                    "t": "μετὰ"
                },
                {
                    "index": "4",
                    "siglum": "Bas",
                    "reading": "Bas",
                    "original": "δὲ",
                    "rule_match": [
                        "δὲ"
                    ],
                    "t": "δὲ"
                },
                {
                    "index": "6",
                    "siglum": "Bas",
                    "reading": "Bas",
                    "original": "τούτων",
                    "rule_match": [
                        "τούτων"
                    ],
                    "t": "τούτων"
                },
                {
                    "index": "8",
                    "siglum": "Bas",
                    "reading": "Bas",
                    "original": "καὶ",
                    "rule_match": [
                        "καὶ"
                    ],
                    "t": "καὶ"
                },
                {
                    "index": "10",
                    "siglum": "Bas",
                    "reading": "Bas",
                    "original": "ἑτέρως",
                    "rule_match": [
                        "ἑτέρως"
                    ],
                    "t": "ἑτέρως"
                },
                {
                    "index": "12",
                    "siglum": "Bas",
                    "reading": "Bas",
                    "original": "σφόδρα",
                    "rule_match": [
                        "σφόδρα"
                    ],
                    "t": "σφόδρα"
                },
                {
                    "index": "14",
                    "siglum": "Bas",
                    "reading": "Bas",
                    "original": "ἔφης",
                    "rule_match": [
                        "ἔφης"
                    ],
                    "t": "ἔφης"
                },
                {
                    "index": "16",
                    "siglum": "Bas",
                    "reading": "Bas",
                    "original": "ἀλγεῖν",
                    "rule_match": [
                        "ἀλγεῖν"
                    ],
                    "t": "ἀλγεῖν"
                },
                {
                    "index": "18",
                    "siglum": "Bas",
                    "reading": "Bas",
                    "original": "ὅτι",
                    "rule_match": [
                        "ὅτι"
                    ],
                    "t": "ὅτι"
                },
                {
                    "index": "20",
                    "siglum": "Bas",
                    "reading": "Bas",
                    "original": "οὕτω",
                    "rule_match": [
                        "οὕτω"
                    ],
                    "t": "οὕτω"
                },
                {
                    "index": "22",
                    "siglum": "Bas",
                    "reading": "Bas",
                    "original": "σου",
                    "rule_match": [
                        "σου"
                    ],
                    "t": "σου"
                },
                {
                    "index": "24",
                    "siglum": "Bas",
                    "reading": "Bas",
                    "original": "τῆς",
                    "rule_match": [
                        "τῆς"
                    ],
                    "t": "τῆς"
                },
                {
                    "index": "26",
                    "siglum": "Bas",
                    "reading": "Bas",
                    "original": "ψυχῆς",
                    "rule_match": [
                        "ψυχῆς"
                    ],
                    "t": "ψυχῆς"
                },
                {
                    "index": "28",
                    "siglum": "Bas",
                    "reading": "Bas",
                    "original": "ἡ",
                    "rule_match": [
                        "ἡ"
                    ],
                    "t": "ἡ"
                },
                {
                    "index": "30",
                    "siglum": "Bas",
                    "reading": "Bas",
                    "original": "τῆς",
                    "rule_match": [
                        "τῆς"
                    ],
                    "t": "τῆς"
                },
                {
                    "index": "32",
                    "siglum": "Bas",
                    "reading": "Bas",
                    "original": "ἀθυμίας",
                    "rule_match": [
                        "ἀθυμίας"
                    ],
                    "t": "ἀθυμίας"
                },
                {
                    "index": "34",
                    "siglum": "Bas",
                    "reading": "Bas",
                    "original": "περιεγένετο",
                    "rule_match": [
                        "περιεγένετο"
                    ],
                    "t": "περιεγένετο"
                },
                {
                    "index": "36",
                    "siglum": "Bas",
                    "reading": "Bas",
                    "original": "δύναμις",
                    "rule_match": [
                        "δύναμις"
                    ],
                    "t": "δύναμις"
                },
                {
                    "index": "38",
                    "siglum": "Bas",
                    "reading": "Bas",
                    "original": "ὡς",
                    "rule_match": [
                        "ὡς"
                    ],
                    "t": "ὡς"
                },
                {
                    "index": "40",
                    "siglum": "Bas",
                    "reading": "Bas",
                    "original": "μικροῦ",
                    "rule_match": [
                        "μικροῦ"
                    ],
                    "t": "μικροῦ"
                },
                {
                    "index": "42",
                    "siglum": "Bas",
                    "reading": "Bas",
                    "original": "πολλάκις",
                    "rule_match": [
                        "πολλάκις"
                    ],
                    "t": "πολλάκις"
                },
                {
                    "index": "44",
                    "siglum": "Bas",
                    "reading": "Bas",
                    "original": "ἐπὶ",
                    "rule_match": [
                        "ἐπὶ"
                    ],
                    "t": "ἐπὶ"
                },
                {
                    "index": "46",
                    "siglum": "Bas",
                    "reading": "Bas",
                    "original": "βρόχον",
                    "rule_match": [
                        "βρόχον"
                    ],
                    "t": "βρόχον"
                },
                {
                    "index": "48",
                    "siglum": "Bas",
                    "reading": "Bas",
                    "original": "ἐλθεῖν",
                    "rule_match": [
                        "ἐλθεῖν"
                    ],
                    "t": "ἐλθεῖν"
                },
                {
                    "index": "50",
                    "siglum": "Bas",
                    "reading": "Bas",
                    "original": "καὶ",
                    "rule_match": [
                        "καὶ"
                    ],
                    "t": "καὶ"
                },
                {
                    "index": "52",
                    "siglum": "Bas",
                    "reading": "Bas",
                    "original": "ἐπὶ",
                    "rule_match": [
                        "ἐπὶ"
                    ],
                    "t": "ἐπὶ"
                },
                {
                    "index": "54",
                    "siglum": "Bas",
                    "reading": "Bas",
                    "original": "ποταμὸν",
                    "rule_match": [
                        "ποταμὸν"
                    ],
                    "t": "ποταμὸν"
                },
                {
                    "index": "56",
                    "siglum": "Bas",
                    "reading": "Bas",
                    "original": "καὶ",
                    "rule_match": [
                        "καὶ"
                    ],
                    "t": "καὶ"
                },
                {
                    "index": "58",
                    "siglum": "Bas",
                    "reading": "Bas",
                    "original": "ἐπὶ",
                    "rule_match": [
                        "ἐπὶ"
                    ],
                    "t": "ἐπὶ"
                },
                {
                    "index": "60",
                    "siglum": "Bas",
                    "reading": "Bas",
                    "original": "κρημνόν",
                    "rule_match": [
                        "κρημνόν"
                    ],
                    "t": "κρημνόν"
                }
            ]
        }
    ]
}